ldap_attributes_selector/__init__.py
ldap_attributes_selector/_version.py
ldap_attributes_selector/ldap_attributes_selector.py
ldap_attributes_selector/ldap_paging.py
ldap_attributes_selector-0.2.7.data/scripts/_version.py
ldap_attributes_selector-0.2.7.dist-info/LICENSE
ldap_attributes_selector-0.2.7.dist-info/METADATA
ldap_attributes_selector-0.2.7.dist-info/WHEEL
ldap_attributes_selector-0.2.7.dist-info/entry_points.txt
ldap_attributes_selector-0.2.7.dist-info/top_level.txt
ldap_attributes_selector-0.2.7.dist-info/RECORD
