Metadata-Version: 2.1
Name: ldap-attributes-selector
Version: 0.2.7
Summary: Get a CSV formatted list, based on a custom set of LDAP attributes.
Home-page: https://github.com/tuxedoar/ldap-attributes-selector
Author: tuxedoar
Author-email: tuxedoar@gmail.com
License: UNKNOWN
Platform: UNKNOWN
Classifier: Programming Language :: Python :: 3 :: Only
Classifier: Programming Language :: Python :: 3.7
Classifier: License :: OSI Approved :: GNU General Public License v3 (GPLv3)
Classifier: Operating System :: OS Independent
Classifier: Intended Audience :: System Administrators
Classifier: Environment :: Console
Classifier: Topic :: System :: Systems Administration :: Authentication/Directory :: LDAP
Requires-Python: >=3.7
Requires-Dist: python-ldap
